{
	"instance" : {
		"reset" : "za 12/26/2008 22:55",
		"parsePossibleDeclaration:" : "za 12/25/2008 06:12",
		"handleData:" : "za 12/10/2008 23:52",
		"parsePossibleOtherTag:" : "za 12/23/2008 04:39",
		"parseStartTagAttribute:into:" : "PaulDeBruicker 2/19/2010 10:43",
		"findInterestingFrom:" : "PaulDeBruicker 2/19/2010 10:41",
		"parsePossibleSpecialTag:" : "za 12/26/2008 22:23",
		"decode" : "za 12/30/2008 04:02",
		"convertCodePoint:" : "za 12/25/2008 01:54",
		"handleComment:" : "za 12/25/2008 07:10",
		"parseProcessingInstruction:" : "sd 1/20/2011 09:23",
		"equals:from:" : "za 12/10/2008 23:06",
		"endData" : "za 12/10/2008 13:05",
		"parsePossibleTag:" : "za 12/23/2008 03:25",
		"replace:using:" : "za 12/9/2008 15:17",
		"handleCharRef:" : "za 12/24/2008 18:22",
		"handleEntityRef:" : "za 12/24/2008 18:21",
		"handleDeclaration:" : "za 12/25/2008 06:41",
		"parsePossibleRef:" : "za 12/26/2008 22:22",
		"initialize" : "CamilloBruni 9/21/2011 16:17",
		"numPops:" : "za 12/23/2008 05:42",
		"popToTag:inclusive:" : "za 12/26/2008 22:52",
		"parseStartTag:" : "PaulDeBruicker 2/19/2010 10:41",
		"parseComment:" : "PaulDeBruicker 2/19/2010 10:42",
		"handleStartTagFrom:to:tag:attrs:" : "za 12/26/2008 22:56",
		"convertEntityRef:" : "za 12/26/2008 23:11",
		"parseIncomplete:" : "PaulDeBruicker 2/19/2010 10:43",
		"parseEntityRef:" : "PaulDeBruicker 2/19/2010 10:42",
		"popTag" : "za 12/26/2008 22:55",
		"pushTag:" : "za 12/26/2008 22:55",
		"massage" : "za 12/9/2008 15:17",
		"parseAny:" : "za 12/23/2008 04:25",
		"handleProcessingInstruction:" : "za 12/25/2008 07:18",
		"parsePossibleLiteral:" : "za 12/23/2008 03:37",
		"parseLiteral:" : "za 12/23/2008 03:52",
		"copy:replace:using:" : "za 2/11/2009 04:26",
		"handleCData:" : "za 12/25/2008 07:02",
		"parseString:" : "sd 1/20/2011 09:23",
		"parameters:" : "za 12/20/2008 11:08",
		"popToTag:" : "za 12/26/2008 22:51",
		"parseCharRef:" : "PaulDeBruicker 2/19/2010 10:42",
		"endData:" : "za 2/15/2009 18:48",
		"handleDataFrom:to:" : "za 12/9/2008 16:14",
		"isNestable:" : "za 12/26/2008 22:37",
		"handleEndTag:" : "za 12/23/2008 06:01",
		"isSelfClosingTag:" : "za 12/20/2008 10:53",
		"parseCData:" : "za 12/26/2008 22:08",
		"parseEndTag:" : "PaulDeBruicker 2/19/2010 10:42",
		"smartPop:" : "za 12/26/2008 22:53",
		"handleEndTagFrom:to:tag:" : "za 12/23/2008 06:01",
		"createRootTag" : "za 12/20/2008 10:56",
		"parsePossibleStartTag:" : "za 12/23/2008 03:23",
		"string:" : "za 12/9/2008 16:11",
		"convertRef:" : "PaulDeBruicker 2/19/2010 10:43",
		"parseDeclaration:" : "PaulDeBruicker 2/19/2010 10:42",
		"parse" : "za 12/26/2008 22:33",
		"isResetNesting:" : "za 12/26/2008 22:35",
		"readStreamFrom:" : "za 12/23/2008 03:05",
		"convertCharRef:" : "za 3/9/2009 16:08"
	},
	"class" : {
		"parameters:" : "za 12/20/2008 11:07"
	}
}